<?xml version="1.0" encoding="UTF-8"?>
<!DOCTYPE TM_orarend SYSTEM "oqh5nh_orarend.dtd">
<TM_orarend>
    <ora id="1" tipus="elmelet">
        <targy>Elektrotechnika, elektronika</targy>
        <idopont>
            <nap>Hétfő</nap>
            <tol>08:00</tol>
            <ig>10:00</ig>
        </idopont>
        <helyszin>3. előadó</helyszin>
        <oktato>Szabó Norbert</oktato>
        <szak>Mérnökinformatikus BSc</szak>
    </ora>
    <ora id="2" tipus="elmelet">
        <targy>Web technológiák I.</targy>
        <idopont>
            <nap>Hétfő</nap>
            <tol>10:00</tol>
            <ig>12:00</ig>
        </idopont>
        <helyszin>5. előadó</helyszin>
        <oktato>Agárdi Anita</oktato>
        <szak>Mérnökinformatikus BSc</szak>
    </ora>
    <ora id="3" tipus="gyakorlat">
        <targy>Angol műszaki szaknyelv I.</targy>
        <idopont>
            <nap>Hétfő</nap>
            <tol>12:00</tol>
            <ig>14:00</ig>
        </idopont>
        <helyszin>A/1 102-103</helyszin>
        <oktato>Nagyné Varga Orsolya</oktato>
        <szak>Mérnökinformatikus BSc</szak>
    </ora>
    <ora id="4" tipus="gyakorlat">
        <targy>Web technológiák I.</targy>
        <idopont>
            <nap>Hétfő</nap>
            <tol>14:00</tol>
            <ig>16:00</ig>
        </idopont>
        <helyszin>Inf. 101</helyszin>
        <oktato>Agárdi Anita</oktato>
        <szak>Mérnökinformatikus BSc</szak>
    </ora>
    <ora id="5" tipus="elmelet">
        <targy>Mobil programozás alapok</targy>
        <idopont>
            <nap>Hétfő</nap>
            <tol>16:00</tol>
            <ig>18:00</ig>
        </idopont>
        <helyszin>Inf. 101</helyszin>
        <oktato>Agárdi Anita</oktato>
        <szak>Mérnökinformatikus BSc</szak>
    </ora>
    <ora id="6" tipus="gyakorlat">
        <targy>Mobil programozás alapok</targy>
        <idopont>
            <nap>Hétfő</nap>
            <tol>18:00</tol>
            <ig>20:00</ig>
        </idopont>
        <helyszin>Inf. 101</helyszin>
        <oktato>Agárdi Anita</oktato>
        <szak>Mérnökinformatikus BSc</szak>
    </ora>

    <ora id="7" tipus="elmelet">
        <targy>Mesterséges intelligencia alapok</targy>
        <idopont>
            <nap>Kedd</nap>
            <tol>10:00</tol>
            <ig>12:00</ig>
        </idopont>
        <helyszin>32. előadó</helyszin>
        <oktato>Kunné Dr. Tamás Judit</oktato>
        <szak>Mérnökinformatikus BSc</szak>
    </ora>
    <ora id="8" tipus="gyakorlat">
        <targy>Mesterséges intelligencia alapok</targy>
        <idopont>
            <nap>Kedd</nap>
            <tol>12:00</tol>
            <ig>14:00</ig>
        </idopont>
        <helyszin>32. előadó</helyszin>
        <oktato>Fazekas Levente Áron</oktato>
        <szak>Mérnökinformatikus BSc</szak>
    </ora>
    <ora id="9" tipus="gyakorlat">
        <targy>Elektrotechnika, elektronika</targy>
        <idopont>
            <nap>Kedd</nap>
            <tol>14:00</tol>
            <ig>16:00</ig>
        </idopont>
        <helyszin>A/1 317</helyszin>
        <oktato>Dr. Kozsely Gábor</oktato>
        <szak>Mérnökinformatikus BSc</szak>
    </ora>
    <ora id="10" tipus="gyakorlat">
        <targy>UNIX rendszergazda</targy>
        <idopont>
            <nap>Kedd</nap>
            <tol>17:00</tol>
            <ig>19:00</ig>
        </idopont>
        <helyszin>Inf. 202</helyszin>
        <oktato>Dr. Baksa Attila</oktato>
        <szak>Mérnökinformatikus BSc</szak>
    </ora>
    <ora id="11" tipus="elmelet">
        <targy>UNIX rendszergazda</targy>
        <idopont>
            <nap>Szerda</nap>
            <tol>08:00</tol>
            <ig>10:00</ig>
        </idopont>
        <helyszin>Inf. 103</helyszin>
        <oktato>Dr. Baksa Attila</oktato>
        <szak>Mérnökinformatikus BSc</szak>
    </ora>
    <ora id="12" tipus="elmelet">
        <targy>Webes adatkezelő környezetek</targy>
        <idopont>
            <nap>Szerda</nap>
            <tol>08:00</tol>
            <ig>10:00</ig>
        </idopont>
        <helyszin>A/1 310</helyszin>
        <oktato>Dr. Kovács László József</oktato>
        <szak>Mérnökinformatikus BSc</szak>
    </ora>
    <ora id="13" tipus="gyakorlat">
        <targy>Webes adatkezelő környezetek</targy>
        <idopont>
            <nap>Szerda</nap>
            <tol>10:00</tol>
            <ig>12:00</ig>
        </idopont>
        <helyszin>A/1 103</helyszin>
        <oktato>Dr. Bednarik László</oktato>
        <szak>Mérnökinformatikus BSc</szak>
    </ora>
</TM_orarend>
